studyfetch_sdk/__init__.py
studyfetch_sdk/_base_client.py
studyfetch_sdk/_client.py
studyfetch_sdk/_compat.py
studyfetch_sdk/_constants.py
studyfetch_sdk/_exceptions.py
studyfetch_sdk/_files.py
studyfetch_sdk/_models.py
studyfetch_sdk/_qs.py
studyfetch_sdk/_resource.py
studyfetch_sdk/_response.py
studyfetch_sdk/_streaming.py
studyfetch_sdk/_types.py
studyfetch_sdk/_version.py
studyfetch_sdk/py.typed
studyfetch_sdk/_utils/__init__.py
studyfetch_sdk/_utils/_compat.py
studyfetch_sdk/_utils/_datetime_parse.py
studyfetch_sdk/_utils/_logs.py
studyfetch_sdk/_utils/_proxy.py
studyfetch_sdk/_utils/_reflection.py
studyfetch_sdk/_utils/_resources_proxy.py
studyfetch_sdk/_utils/_streams.py
studyfetch_sdk/_utils/_sync.py
studyfetch_sdk/_utils/_transform.py
studyfetch_sdk/_utils/_typing.py
studyfetch_sdk/_utils/_utils.py
studyfetch_sdk/lib/.keep
studyfetch_sdk/resources/__init__.py
studyfetch_sdk/resources/v1/__init__.py
studyfetch_sdk/resources/v1/chat.py
studyfetch_sdk/resources/v1/chat_analytics.py
studyfetch_sdk/resources/v1/components.py
studyfetch_sdk/resources/v1/folders.py
studyfetch_sdk/resources/v1/usage.py
studyfetch_sdk/resources/v1/usage_analyst.py
studyfetch_sdk/resources/v1/v1.py
studyfetch_sdk/resources/v1/assignment_grader/__init__.py
studyfetch_sdk/resources/v1/assignment_grader/assignment_grader.py
studyfetch_sdk/resources/v1/assignment_grader/rubric_templates.py
studyfetch_sdk/resources/v1/embed/__init__.py
studyfetch_sdk/resources/v1/embed/component.py
studyfetch_sdk/resources/v1/embed/context.py
studyfetch_sdk/resources/v1/embed/embed.py
studyfetch_sdk/resources/v1/materials/__init__.py
studyfetch_sdk/resources/v1/materials/bulk.py
studyfetch_sdk/resources/v1/materials/materials.py
studyfetch_sdk/resources/v1/materials/upload.py
studyfetch_sdk/resources/v1/pdf_generator/__init__.py
studyfetch_sdk/resources/v1/pdf_generator/pdf_generator.py
studyfetch_sdk/types/__init__.py
studyfetch_sdk/types/v1/__init__.py
studyfetch_sdk-0.1.0a33.dist-info/METADATA
studyfetch_sdk-0.1.0a33.dist-info/WHEEL
studyfetch_sdk-0.1.0a33.dist-info/licenses/LICENSE
studyfetch_sdk-0.1.0a33.dist-info/RECORD
